Workbook

Sheet Sheet1
C5: Cost Comparision App Engagement Platform
D7: Pushwoosh (in USD) | E7: Pushwoosh (in Cr. INR @98) | F7: Plotline (in Cr) | G7: Purpletalk (in Cr)
C8: 1st Year Cost | D8: ='Price Comparison '!P13 -> 39000 | E8: =D8*98/10^7 -> 0.3822 | F8: ='Price Comparison '!E13/10^7 -> 0.9987368 | G8: ='Price Comparison '!J13/10^7 -> 5.892
C9: 2nd year Cost | D9: ='Price Comparison '!Q13 -> 42335.789 | E9: =D9*98/10^7 -> 0.41489073 | F9: ='Price Comparison '!F13/10^7 -> 1.0436105 | G9: ='Price Comparison '!K13/10^7 -> 5.9352
C10: 3rd Year Cosgt | D10: ='Price Comparison '!R13 -> 45948 | E10: =D10*98/10^7 -> 0.4502904 | F10: ='Price Comparison '!G13/10^7 -> 1.1479715 | G10: ='Price Comparison '!L13/10^7 -> 5.98272
D11: =SUM(D8:D10) -> 127283.79 | E11: =SUM(E8:E10) -> 1.2473811 | F11: =SUM(F8:F10) -> 3.1903188 | G11: =SUM(G8:G10) -> 17.80992
D12: L1 | F12: L2 | G12: L3
D13: T3 | F13: T1 | G13: T2

Sheet Price Comparison 
B3: Final Round (Revised Scope)
N5: 1
B6: Price Comparison - App Engagement Platform
B7: Figures in INR | D7: Plotline | I7: Purple Talk | N7: Pushwoosh
B8: Description of services | C8: Unit | D8: Quantity | E8: Year 1 | F8: Year 2 | G8: Year 3 | H8: Total Price (3 Year) | I8: Description of services | J8: Year 1 | K8: Year 2 | L8: Year 3 | M8: Total Price (3 Year) | N8: Description of services | O8: Qty | P8: Year 1 | Q8: Year 2 | R8: Year 3 | S8: Total Price (3 Year)
B9: In‑App Platform – Fixed Fee | C9: Monthly | D9: 12 | E9: =(2400000*0.15972*D9)+(2400000*0.03993*D9) -> 5749920 | F9: =(2640000*0.15972*D9)++(2640000*0.03993*D9) -> 6324912 | G9: =(2904000*0.15972*D9)++(2904000*0.03993*D9) -> 6957403.2 | H9: =SUM(E9:G9) -> 19032235 | I9: Platform Cost | J9: =4500000*12 -> 54000000 | K9: =J9 -> 54000000 | L9: =K9 -> 54000000 | M9: =SUM(J9:L9) -> 162000000 | N9: License subscription Cost - In‑App Platform – Fixed Fee | O9: EA | P9: =0.00125*2400000*12*N5 -> 36000 | Q9: =0.00124166*2640000*12*N5 -> 39335.789 | R9: =0.00123243802*2904000*12*N5 -> 42948 | S9: =SUM(P9:R9) -> 118283.79
B10: Plotline Off‑App Platform – Fixed Fee Include Push Notification | C10: Monthly | D10: 12 | E10: =2400000*0.099825*D10 -> 2874960 | F10: =2640000*0.099825*D10 -> 3162456 | G10: =2904000*0.099825*D10 -> 3478701.6 | H10: =SUM(E10:G10) -> 9516117.6 | I10: MAU Cost Per Month | J10: =0.15*2400000 *12 -> 4320000 | K10: =0.15*2640000*12 -> 4752000 | L10: =0.15*2904000*12 -> 5227200 | M10: =SUM(J10:L10) -> 14299200 | N10: One time Cost - Onboarding Fees | O10: EA | P10: 0 | Q10: 0 | R10: 0 | S10: =SUM(P10:R10) -> 0
B11: Enterprise Support (optional) | C11: Monthly | D11: 1 | E11: =((E9+E10)*10%) -> 862488 | F11: =((F9+F10)*10%)*D11 -> 948736.8 | G11: =((G9+G10)*10%)*D11 -> 1043610.5 | H11: =SUM(E11:G11) -> 2854835.3 | I11: Support up to 30 hours | J11: =50000*12 -> 600000 | K11: =J11 -> 600000 | L11: =K11 -> 600000 | M11: =SUM(J11:L11) -> 1800000 | N11: Overage Cost (MAU above committed band) per 1000 MAU | O11: EA | P11: =2.5*N5 -> 2.5 | S11: =SUM(P11:R11) -> 2.5
B12: Implementation | D12: 1 | E12: 500000 | F12: 0 | G12: 0 | H12: =SUM(E12:G12) -> 500000 | I12: Additional Development (per hour) | J12: 2000 | K12: 0 | L12: 0 | M12: 0 | N12: Support | O12: EA | P12: =250*N5*12 -> 3000 | Q12: =P12 -> 3000 | R12: =Q12 -> 3000 | S12: =SUM(P12:R12) -> 9000
B13: Total | C13: EA | D13: 1 | E13: =SUM(E9:E12) -> 9987368 | F13: =SUM(F9:F12) -> 10436105 | G13: =SUM(G9:G12) -> 11479715 | H13: =SUM(H9:H12) -> 31903188 | J13: =SUM(J9:J11) -> 58920000 | K13: =SUM(K9:K11) -> 59352000 | L13: =SUM(L9:L11) -> 59827200 | M13: =SUM(J13:L13) -> 178099200 | P13: =SUM(P9:P12)-P11 -> 39000 | Q13: =SUM(Q9:Q12)-Q11 -> 42335.789 | R13: =SUM(R9:R12)-R11 -> 45948 | S13: =SUM(P13:R13) -> 127283.79
T14: INR
B15: Grand Total Cost | H15: =H13 -> 31903188 | M15: =M13 -> 178099200 | S15: =S13 -> 127283.79 | T15: =S15*96 -> 12219244
G17: L2 | H17: T1 | L17: L3 | M17: T2 | R17: L1 | S17: T3
D22: Plotline Comment | K22: Purplie Talk Comment | O22: Pushwoosh Comment
C23: Price Escalation | D23: Pricing for the first 3 years will remain the same, considering this is a 3-year contract. Upon renewal, any price increase will be capped at a maximum of 5%, subject to mutual discussion and agreement at the time of renewal. | J23: Price Escalation | K23: 10% increment per year | N23: Price Escalation | O23: Confirmed. Unit price is locked for the full 3-year term as per the table above.
C24: Billing Frequency | D24: Minimum billing terms would be quarterly prepaid. | J24: Billing Frequency | K24: Monthly | N24: Billing Frequency | O24: Monthly
C25: Pricing Model | D25: There will be no price overage as long as the MAU scope and overall scope remains the same as mentioned in the scope/ RFP document. | J25: Pricing Model | K25: Fixed for 10 million MAU only. | N25: Pricing Model | O25: Fixed monthly fee per MAU tier + overage at $2.50 / 1,000 MAU.
C26: Auto Renewal | D26: No | J26: Auto Renewal | K26: Up to Indigo's conditions | N26: Auto Renewal | O26: No auto-renewal. Contract expires at end of term.
C27: Contract term | D27: 3 Year | J27: Contract term | K27: 3 Years | N27: Contract term | O27: 37 months (1 month onboarding + 36 months subscription).
C28: Payment Term | D28: TOP can be a maximum of 45 days, considering we are an MSME. | J28: Payment Term | K28: 45 days(Flexible) | N28: Payment Term | O28: Net-60 from receipt of invoice.
C29: Contract Currency | D29: INR | J29: Contract Currency | K29: INR | N29: TRC, TRD & E10F documents) | O29: We are currently confirming availability of the relevant tax residency documentation for cross-border transactions with India. We will revert within 2 business days.
C30: Implementation Period and Man Efforts | D30: 30 days | J30: SLA | K30: As per the RFP Scope and Upshot conditions | N30: Contract Currency | O30: We propose to invoice in USD, with the exchange rate fixed at the date of contract signing. This is our standard practice for international contracts and avoids currency fluctuation risk for both parties. We are open to discussing this further.
C31: SLA | D31: As per RFP Scope | J31: SLA Credit | K31: As per the RPF Scope (will revisit and confirm) | N31: Termination for Convenience | O31: We can accommodate a Termination for Convenience clause with a standard 90-day written notice period.
C32: SLA Credit | D32: As per RPF Scope | J32: Termination for Convenience | K32: Yes (60 days advance notice)
C33: Termination for Convenience | D33: 30 days advance notice
